{
  "brand": {
    "name_en": "PetSpot El Sahel",
    "name_ar": "بيت سبوت الساحل",
    "legal_name": "Pet Spot Veterinary Clinic",
    "tagline_en": "Trusted Pet Care in El Sahel",
    "tagline_ar": "رعاية بيطرية موثوقة لحيوانك الأليف في الساحل",
    "subheadline_en": "Veterinary care, grooming, boarding & vaccinations — Amwaj 1, North Coast.",
    "subheadline_ar": "كشف بيطري، تطعيمات، جروومينج وبوردينج — أمواج 1، الساحل الشمالي.",
    "positioning_en": "Your pet's trusted summer care destination on Egypt's North Coast — clinic, grooming, boarding, and pet care in one place.",
    "positioning_ar": "وجهتكم الموثوقة لرعاية أليفكم في الساحل — عيادة، جروومينج، بوردينج، وخدمات رعاية في مكان واحد."
  },
  "contact": {
    "phone_primary": "+201201568888",
    "phone_alternate": "+201000059085",
    "phone_note": "TODO: Confirm official campaign number — sources list 01000059085 and 01201568888",
    "whatsapp": "201201568888",
    "email": "vetelsahel@gmail.com",
    "email_alternate": "animalcarecenterpetspots@gmail.com",
    "facebook": "https://www.facebook.com/animalcarecenterpetspots/",
    "instagram": "https://www.instagram.com/pet_spot_clinic/",
    "google_maps": "https://maps.app.goo.gl/AaHup6NEFodZEs7S7"
  },
  "location": {
    "area_en": "Amwaj 1, North Coast — Sidi Abdel Rahman",
    "area_ar": "أمواج 1، الساحل الشمالي — سيدي عبد الرحمن",
    "address_en": "Beside Amwaj 1 gate, Main Road, Sidi Abdel Rahman, North Coast",
    "address_ar": "بجوار بوابة أمواج 1، الطريق الرئيسي، سيدي عبد الرحمن، الساحل الشمالي",
    "address_note": "Confirmed — Google Maps pin beside Amwaj 1 gate on the main road",
    "hours_en": "Summer season · Open daily",
    "hours_ar": "موسم الصيف · مفتوح يومياً"
  },
  "seo": {
    "title": "PetSpot El Sahel | Veterinary Clinic, Grooming & Boarding",
    "description": "PetSpot El Sahel provides veterinary consultations, vaccinations, grooming, boarding, and home visits for pets in the North Coast."
  },
  "services": [
    {
      "id": "consultation",
      "title_en": "Veterinary Consultation",
      "title_ar": "كشف بيطري",
      "desc_en": "Expert exams for cats, dogs, and exotic pets.",
      "desc_ar": "كشف متخصص للقطط والكلاب والحيوانات الأليفة.",
      "cta_en": "Book on WhatsApp",
      "cta_ar": "احجز على واتساب",
      "icon": "fa-stethoscope",
      "color": "#1a5f7a",
      "gallery_slot": "veterinary"
    },
    {
      "id": "vaccination",
      "title_en": "Vaccination",
      "title_ar": "تطعيمات",
      "desc_en": "Keep your pet protected before and during vacation.",
      "desc_ar": "حماية أليفك قبل وأثناء الإجازة.",
      "cta_en": "Book on WhatsApp",
      "cta_ar": "احجز على واتساب",
      "icon": "fa-medkit",
      "color": "#2d8f6f",
      "gallery_slot": "clinic_front"
    },
    {
      "id": "grooming",
      "title_en": "Grooming",
      "title_ar": "جروومينج",
      "desc_en": "Professional grooming for a fresh summer look.",
      "desc_ar": "جرومينج احترافي لمظهر صيفي أنيق.",
      "cta_en": "Book on WhatsApp",
      "cta_ar": "احجز على واتساب",
      "icon": "fa-scissors",
      "color": "#c45c3e",
      "gallery_slot": "grooming"
    },
    {
      "id": "boarding",
      "title_en": "Boarding",
      "title_ar": "بوردينج",
      "desc_en": "Safe supervised stay while you enjoy the coast.",
      "desc_ar": "إقامة آمنة تحت الإشراف أثناء استمتاعكم بالساحل.",
      "cta_en": "Book on WhatsApp",
      "cta_ar": "احجز على واتساب",
      "icon": "fa-home",
      "color": "#3d5a80",
      "gallery_slot": "boarding"
    },
    {
      "id": "home_visit",
      "title_en": "Home Visit",
      "title_ar": "زيارة منزلية",
      "desc_en": "Mobile vet care for North Coast compounds.",
      "desc_ar": "رعاية بيطرية متنقلة لكمبوندات الساحل.",
      "cta_en": "Book on WhatsApp",
      "cta_ar": "احجز على واتساب",
      "icon": "fa-ambulance",
      "color": "#5c4d7d"
    },
    {
      "id": "pet_supplies",
      "title_en": "Pet Supplies",
      "title_ar": "مستلزمات الحيوانات",
      "desc_en": "Pet shop essentials when available on site.",
      "desc_ar": "مستلزمات الحيوانات الأليفة في المكان.",
      "cta_en": "Call us",
      "cta_ar": "اتصل بنا",
      "icon": "fa-shopping-basket",
      "color": "#b8860b"
    }
  ],
  "gallery_slots": [
    {"id": "clinic_front", "alt": "PetSpot El Sahel clinic front", "file": "clinic-front.jpg"},
    {"id": "grooming", "alt": "PetSpot grooming area", "file": "grooming-area.jpg"},
    {"id": "boarding", "alt": "PetSpot boarding area", "file": "boarding-area.jpg"},
    {"id": "veterinary", "alt": "PetSpot veterinary care", "file": "veterinary-care.jpg"}
  ],
  "gallery_extra_count": 12,
  "logo": {
    "path": "assets/logo/petspot-logo.png",
    "source": "assets/logo/logo.svg",
    "note": "Edit logo.svg then run deploy.py — PNG is auto-generated for Odoo"
  }
}
